{"files":{"apps/web/.next/server":{"size":0,"mtime_nanos":0,"mode":0,"is_dir":true},"apps/web/.next/server/next-font-manifest.json":{"size":77,"mtime_nanos":1779722753314354000,"mode":420,"is_dir":false},"apps/web/.next/server/pages-manifest.json":{"size":111,"mtime_nanos":1779722766784833200,"mode":420,"is_dir":false},"apps/web/.next/server/server-reference-manifest.js":{"size":123,"mtime_nanos":1779722740148903200,"mode":420,"is_dir":false},"apps/web/.next/static/Du1pxD_hUXuMQ9yq-H1VP/_ssgManifest.js":{"size":80,"mtime_nanos":1779722766795833800,"mode":420,"is_dir":false},"apps/web/.next/cache/webpack/server-production":{"size":0,"mtime_nanos":0,"mode":0,"is_dir":true},"apps/web/.next/static/chunks/app/_not-found":{"size":0,"mtime_nanos":0,"mode":0,"is_dir":true},"apps/web/.next/static/chunks/app/layout-957b87a577922aef.js":{"size":1474,"mtime_nanos":1779722753307663200,"mode":420,"is_dir":false},"apps/web/.next/static/chunks/app/page-d664a2721904a2dd.js":{"size":53988,"mtime_nanos":1779722753308664900,"mode":420,"is_dir":false},"apps/web/.next/static/chunks/pages":{"size":0,"mtime_nanos":0,"mode":0,"is_dir":true},"apps/web/.next/server/webpack-runtime.js":{"size":1459,"mtime_nanos":1779722740144175000,"mode":420,"is_dir":false},"apps/web/.next/static/css":{"size":0,"mtime_nanos":0,"mode":0,"is_dir":true},"apps/web/.next/static/media":{"size":0,"mtime_nanos":0,"mode":0,"is_dir":true},"apps/web/.next/server/app/_not-found.html":{"size":8341,"mtime_nanos":1779722766443228700,"mode":420,"is_dir":false},"apps/web/.next/static/media/9e7b0a821b9dfcb4-s.woff2":{"size":21688,"mtime_nanos":1779722753302667700,"mode":420,"is_dir":false},"apps/web/.next/server/middleware-manifest.json":{"size":83,"mtime_nanos":1779722745931197700,"mode":420,"is_dir":false},"apps/web/.next/types/app/layout.ts":{"size":3474,"mtime_nanos":1779722740148903200,"mode":420,"is_dir":false},"apps/web/.next/package.json":{"size":20,"mtime_nanos":1779722731984501200,"mode":420,"is_dir":false},"apps/web/.next/server/chunks/font-manifest.json":{"size":2,"mtime_nanos":1779722740141754100,"mode":420,"is_dir":false},"apps/web/.next/server/app/_not-found/page.js":{"size":4499,"mtime_nanos":1779722740147883600,"mode":420,"is_dir":false},"apps/web/.next/server/pages/404.html":{"size":8341,"mtime_nanos":1779722766443228700,"mode":420,"is_dir":false},"apps/web/.next/static/chunks/5b8f0dd8-dcb4dfab7f3f9cf5.js":{"size":172833,"mtime_nanos":1779722753309662800,"mode":420,"is_dir":false},"apps/web/.next/static/media/c5fe6dc8356a8c31-s.woff2":{"size":11272,"mtime_nanos":1779722753303671100,"mode":420,"is_dir":false},"apps/web/.next/static/Du1pxD_hUXuMQ9yq-H1VP/_buildManifest.js":{"size":224,"mtime_nanos":1779722753313351100,"mode":420,"is_dir":false},"apps/web/.next/static/chunks/main-app-85d0d6820989dc6e.js":{"size":463,"mtime_nanos":1779722753303671100,"mode":420,"is_dir":false},"apps/web/.next/server/app/index.meta":{"size":80,"mtime_nanos":1779722766714169200,"mode":420,"is_dir":false},"apps/web/.next/cache/webpack/edge-server-production":{"size":0,"mtime_nanos":0,"mode":0,"is_dir":true},"apps/web/.next/static/chunks/polyfills-42372ed130431b0a.js":{"size":112594,"mtime_nanos":1779722753310664200,"mode":420,"is_dir":false},"apps/web/.next/cache/swc":{"size":0,"mtime_nanos":0,"mode":0,"is_dir":true},"apps/web/.next/server/pages/_document.js":{"size":378,"mtime_nanos":1779722740144175000,"mode":420,"is_dir":false},"apps/web/.next/cache/webpack/edge-server-production/0.pack":{"size":274,"mtime_nanos":1779722746703665200,"mode":420,"is_dir":false},"apps/web/.next/static/media/e4af272ccee01ff0-s.p.woff2":{"size":48432,"mtime_nanos":1779722753303671100,"mode":420,"is_dir":false},"apps/web/.next/static/chunks/framework-bef83a85c94ff7de.js":{"size":139981,"mtime_nanos":1779722753309662800,"mode":420,"is_dir":false},"apps/web/.next/cache/swc/plugins/v7_windows_x86_64_0.106.15":{"size":0,"mtime_nanos":0,"mode":0,"is_dir":true},"apps/web/.next/static/media/8ebc6e9dde468c4a-s.woff2":{"size":8292,"mtime_nanos":1779722753303671100,"mode":420,"is_dir":false},"apps/web/.next/server/app/_not-found.meta":{"size":142,"mtime_nanos":1779722766448296900,"mode":420,"is_dir":false},"apps/web/.next/react-loadable-manifest.json":{"size":2,"mtime_nanos":1779722753307663200,"mode":420,"is_dir":false},"apps/web/.next/server/app-paths-manifest.json":{"size":76,"mtime_nanos":1779722745907082100,"mode":420,"is_dir":false},"apps/web/.next/static/css/68c75141fb380fcd.css":{"size":44956,"mtime_nanos":1779722753315353500,"mode":420,"is_dir":false},"apps/web/.next/static/media/6fe53d21e6e7ebd8-s.woff2":{"size":1716,"mtime_nanos":1779722753302667700,"mode":420,"is_dir":false},"apps/web/.next/server/chunks":{"size":0,"mtime_nanos":0,"mode":0,"is_dir":true},"apps/web/.next/static/media/ba9851c3c22cd980-s.woff2":{"size":25844,"mtime_nanos":1779722753303671100,"mode":420,"is_dir":false},"apps/web/.next/types":{"size":0,"mtime_nanos":0,"mode":0,"is_dir":true},"apps/web/.next/types/package.json":{"size":18,"mtime_nanos":1779722740148903200,"mode":420,"is_dir":false},"apps/web/.next/trace":{"size":877603,"mtime_nanos":1779722767069429200,"mode":420,"is_dir":false},"apps/web/.next/export-marker.json":{"size":94,"mtime_nanos":1779722766800743300,"mode":420,"is_dir":false},"apps/web/.next/server/middleware-react-loadable-manifest.js":{"size":36,"mtime_nanos":1779722753310664200,"mode":420,"is_dir":false},"apps/web/.next/static":{"size":0,"mtime_nanos":0,"mode":0,"is_dir":true},"apps/web/.next/server/font-manifest.json":{"size":2,"mtime_nanos":1779722740144175000,"mode":420,"is_dir":false},"apps/web/.next/build-manifest.json":{"size":968,"mtime_nanos":1779722753308664900,"mode":420,"is_dir":false},"apps/web/.next/static/Du1pxD_hUXuMQ9yq-H1VP":{"size":0,"mtime_nanos":0,"mode":0,"is_dir":true},"apps/web/.next/images-manifest.json":{"size":511,"mtime_nanos":1779722766798208000,"mode":420,"is_dir":false},"apps/web/.next/server/app/_not-found":{"size":0,"mtime_nanos":0,"mode":0,"is_dir":true},"apps/web/.next/server/next-font-manifest.js":{"size":106,"mtime_nanos":1779722753314354000,"mode":420,"is_dir":false},"apps/web/.next/static/chunks/main-396265f3b83d3285.js":{"size":116407,"mtime_nanos":1779722753304667500,"mode":420,"is_dir":false},"apps/web/.next/static/media/21350d82a1f187e9-s.woff2":{"size":18744,"mtime_nanos":1779722753303671100,"mode":420,"is_dir":false},"apps/web/.next/next-minimal-server.js.nft.json":{"size":4717,"mtime_nanos":1779722766063754200,"mode":420,"is_dir":false},"apps/web/.next/server/pages":{"size":0,"mtime_nanos":0,"mode":0,"is_dir":true},"apps/web/.next/static/chunks/pages/_app-32ee63fa91347547.js":{"size":280,"mtime_nanos":1779722753304667500,"mode":420,"is_dir":false},"apps/web/.next/server/pages/_app.js":{"size":3293,"mtime_nanos":1779722740144175000,"mode":420,"is_dir":false},"apps/web/.next/static/chunks/app/_not-found/page-b60d01030822dcd7.js":{"size":1745,"mtime_nanos":1779722753311342400,"mode":420,"is_dir":false},"apps/web/.next/server/app/_not-found.rsc":{"size":4558,"mtime_nanos":1779722766438668800,"mode":420,"is_dir":false},"apps/web/.next/static/chunks/app":{"size":0,"mtime_nanos":0,"mode":0,"is_dir":true},"apps/web/.next/static/media/636a5ac981f94f8b-s.p.woff2":{"size":27272,"mtime_nanos":1779722753302667700,"mode":420,"is_dir":false},"apps/web/.next/server/middleware-build-manifest.js":{"size":888,"mtime_nanos":1779722753312350100,"mode":420,"is_dir":false},"apps/web/.next/app-path-routes-manifest.json":{"size":46,"mtime_nanos":1779722763030902200,"mode":420,"is_dir":false},"apps/web/.next/server/app/page.js.nft.json":{"size":176,"mtime_nanos":1779722765986567100,"mode":420,"is_dir":false},"apps/web/.next/static/media/8e9860b6e62d6359-s.woff2":{"size":85272,"mtime_nanos":1779722753304667500,"mode":420,"is_dir":false},"apps/web/.next/static/chunks/587-08f4aa1680cdf0e7.js":{"size":153772,"mtime_nanos":1779722753309662800,"mode":420,"is_dir":false},"apps/web/.next/routes-manifest.json":{"size":721,"mtime_nanos":1779722731988190300,"mode":420,"is_dir":false},"apps/web/.next/server/interception-route-rewrite-manifest.js":{"size":48,"mtime_nanos":1779722745931197700,"mode":420,"is_dir":false},"apps/web/.next/types/app/page.ts":{"size":3462,"mtime_nanos":1779722740149903700,"mode":420,"is_dir":false},"apps/web/.next/cache/.tsbuildinfo":{"size":125036,"mtime_nanos":1779722761369049800,"mode":420,"is_dir":false},"apps/web/.next/app-build-manifest.json":{"size":958,"mtime_nanos":1779722753314354000,"mode":420,"is_dir":false},"apps/web/.next/server/pages/_error.js":{"size":8619,"mtime_nanos":1779722740144175000,"mode":420,"is_dir":false},"apps/web/.next/server/pages/_error.js.nft.json":{"size":146,"mtime_nanos":1779722765986567100,"mode":420,"is_dir":false},"apps/web/.next/server/server-reference-manifest.json":{"size":84,"mtime_nanos":1779722740149903700,"mode":420,"is_dir":false},"apps/web/.next/server/app":{"size":0,"mtime_nanos":0,"mode":0,"is_dir":true},"apps/web/.next/static/chunks/webpack-843aca0629275769.js":{"size":3446,"mtime_nanos":1779722753308664900,"mode":420,"is_dir":false},"apps/web/.next/cache/webpack/edge-server-production/index.pack":{"size":21275,"mtime_nanos":1779722746705668600,"mode":420,"is_dir":false},"apps/web/.next/static/media/19cfc7226ec3afaa-s.woff2":{"size":19044,"mtime_nanos":1779722753303671100,"mode":420,"is_dir":false},"apps/web/.next/types/app":{"size":0,"mtime_nanos":0,"mode":0,"is_dir":true},"apps/web/.next/cache/swc/plugins":{"size":0,"mtime_nanos":0,"mode":0,"is_dir":true},"apps/web/.next/cache/webpack/server-production/index.pack":{"size":7117879,"mtime_nanos":1779722743301054500,"mode":420,"is_dir":false},"apps/web/.next/prerender-manifest.json":{"size":526,"mtime_nanos":1779722766791836600,"mode":420,"is_dir":false},"apps/web/.next/server/app/index.html":{"size":95748,"mtime_nanos":1779722766711964800,"mode":420,"is_dir":false},"apps/web/.next/server/app/page.js":{"size":200183,"mtime_nanos":1779722740146507400,"mode":420,"is_dir":false},"apps/web/.next/cache/webpack/client-production":{"size":0,"mtime_nanos":0,"mode":0,"is_dir":true},"apps/web/.next/server/chunks/754.js":{"size":154144,"mtime_nanos":1779722740142755900,"mode":420,"is_dir":false},"apps/web/.next/server/pages/_app.js.nft.json":{"size":228,"mtime_nanos":1779722765985569300,"mode":420,"is_dir":false},"apps/web/.turbo/turbo-build.log":{"size":1332,"mtime_nanos":1779722767140892300,"mode":420,"is_dir":false},"apps/web/.next":{"size":0,"mtime_nanos":0,"mode":0,"is_dir":true},"apps/web/.next/server/app/index.rsc":{"size":3232,"mtime_nanos":1779722766708593000,"mode":420,"is_dir":false},"apps/web/.next/BUILD_ID":{"size":21,"mtime_nanos":1779722764902209100,"mode":420,"is_dir":false},"apps/web/.next/static/chunks/749-c3c6a649b028c872.js":{"size":124362,"mtime_nanos":1779722753311342400,"mode":420,"is_dir":false},"apps/web/.next/server/app/page_client-reference-manifest.js":{"size":5072,"mtime_nanos":1779722753315353500,"mode":420,"is_dir":false},"apps/web/.next/server/functions-config-manifest.json":{"size":28,"mtime_nanos":1779722764854557500,"mode":420,"is_dir":false},"apps/web/.next/server/app/_not-found/page.js.nft.json":{"size":164,"mtime_nanos":1779722765985569300,"mode":420,"is_dir":false},"apps/web/.next/server/pages/_document.js.nft.json":{"size":281,"mtime_nanos":1779722765986567100,"mode":420,"is_dir":false},"apps/web/.next/static/media/df0a9ae256c0569c-s.woff2":{"size":10280,"mtime_nanos":1779722753303671100,"mode":420,"is_dir":false},"apps/web/.next/static/chunks/pages/_error-79ee453ce9bad74d.js":{"size":247,"mtime_nanos":1779722753304667500,"mode":420,"is_dir":false},"apps/web/.next/static/chunks":{"size":0,"mtime_nanos":0,"mode":0,"is_dir":true},"apps/web/.next/server/chunks/192.js":{"size":33640,"mtime_nanos":1779722740142755900,"mode":420,"is_dir":false},"apps/web/.next/server/app/_not-found/page_client-reference-manifest.js":{"size":5146,"mtime_nanos":1779722753315353500,"mode":420,"is_dir":false},"apps/web/.next/required-server-files.json":{"size":4633,"mtime_nanos":1779722764908202900,"mode":420,"is_dir":false},"apps/web/.next/cache/webpack/client-production/0.pack":{"size":32272227,"mtime_nanos":1779722757650271300,"mode":420,"is_dir":false},"apps/web/.next/cache":{"size":0,"mtime_nanos":0,"mode":0,"is_dir":true},"apps/web/.next/next-server.js.nft.json":{"size":4695,"mtime_nanos":1779722766063754200,"mode":420,"is_dir":false},"apps/web/.next/server/pages/500.html":{"size":1995,"mtime_nanos":1779722766463808000,"mode":420,"is_dir":false},"apps/web/.next/cache/webpack/server-production/0.pack":{"size":24666698,"mtime_nanos":1779722743777269200,"mode":420,"is_dir":false},"apps/web/.next/cache/webpack":{"size":0,"mtime_nanos":0,"mode":0,"is_dir":true},"apps/web/.next/cache/webpack/client-production/index.pack":{"size":9810447,"mtime_nanos":1779722757060249900,"mode":420,"is_dir":false}},"order":["apps/web/.next","apps/web/.next/BUILD_ID","apps/web/.next/app-build-manifest.json","apps/web/.next/app-path-routes-manifest.json","apps/web/.next/build-manifest.json","apps/web/.next/cache","apps/web/.next/cache/.tsbuildinfo","apps/web/.next/cache/swc","apps/web/.next/cache/swc/plugins","apps/web/.next/cache/swc/plugins/v7_windows_x86_64_0.106.15","apps/web/.next/cache/webpack","apps/web/.next/cache/webpack/client-production","apps/web/.next/cache/webpack/client-production/0.pack","apps/web/.next/cache/webpack/client-production/index.pack","apps/web/.next/cache/webpack/edge-server-production","apps/web/.next/cache/webpack/edge-server-production/0.pack","apps/web/.next/cache/webpack/edge-server-production/index.pack","apps/web/.next/cache/webpack/server-production","apps/web/.next/cache/webpack/server-production/0.pack","apps/web/.next/cache/webpack/server-production/index.pack","apps/web/.next/export-marker.json","apps/web/.next/images-manifest.json","apps/web/.next/next-minimal-server.js.nft.json","apps/web/.next/next-server.js.nft.json","apps/web/.next/package.json","apps/web/.next/prerender-manifest.json","apps/web/.next/react-loadable-manifest.json","apps/web/.next/required-server-files.json","apps/web/.next/routes-manifest.json","apps/web/.next/server","apps/web/.next/server/app","apps/web/.next/server/app/_not-found","apps/web/.next/server/app/_not-found/page.js","apps/web/.next/server/app/_not-found/page.js.nft.json","apps/web/.next/server/app/_not-found/page_client-reference-manifest.js","apps/web/.next/server/app/_not-found.html","apps/web/.next/server/app/_not-found.meta","apps/web/.next/server/app/_not-found.rsc","apps/web/.next/server/app/index.html","apps/web/.next/server/app/index.meta","apps/web/.next/server/app/index.rsc","apps/web/.next/server/app/page.js","apps/web/.next/server/app/page.js.nft.json","apps/web/.next/server/app/page_client-reference-manifest.js","apps/web/.next/server/app-paths-manifest.json","apps/web/.next/server/chunks","apps/web/.next/server/chunks/192.js","apps/web/.next/server/chunks/754.js","apps/web/.next/server/chunks/font-manifest.json","apps/web/.next/server/font-manifest.json","apps/web/.next/server/functions-config-manifest.json","apps/web/.next/server/interception-route-rewrite-manifest.js","apps/web/.next/server/middleware-build-manifest.js","apps/web/.next/server/middleware-manifest.json","apps/web/.next/server/middleware-react-loadable-manifest.js","apps/web/.next/server/next-font-manifest.js","apps/web/.next/server/next-font-manifest.json","apps/web/.next/server/pages","apps/web/.next/server/pages/404.html","apps/web/.next/server/pages/500.html","apps/web/.next/server/pages/_app.js","apps/web/.next/server/pages/_app.js.nft.json","apps/web/.next/server/pages/_document.js","apps/web/.next/server/pages/_document.js.nft.json","apps/web/.next/server/pages/_error.js","apps/web/.next/server/pages/_error.js.nft.json","apps/web/.next/server/pages-manifest.json","apps/web/.next/server/server-reference-manifest.js","apps/web/.next/server/server-reference-manifest.json","apps/web/.next/server/webpack-runtime.js","apps/web/.next/static","apps/web/.next/static/Du1pxD_hUXuMQ9yq-H1VP","apps/web/.next/static/Du1pxD_hUXuMQ9yq-H1VP/_buildManifest.js","apps/web/.next/static/Du1pxD_hUXuMQ9yq-H1VP/_ssgManifest.js","apps/web/.next/static/chunks","apps/web/.next/static/chunks/587-08f4aa1680cdf0e7.js","apps/web/.next/static/chunks/5b8f0dd8-dcb4dfab7f3f9cf5.js","apps/web/.next/static/chunks/749-c3c6a649b028c872.js","apps/web/.next/static/chunks/app","apps/web/.next/static/chunks/app/_not-found","apps/web/.next/static/chunks/app/_not-found/page-b60d01030822dcd7.js","apps/web/.next/static/chunks/app/layout-957b87a577922aef.js","apps/web/.next/static/chunks/app/page-d664a2721904a2dd.js","apps/web/.next/static/chunks/framework-bef83a85c94ff7de.js","apps/web/.next/static/chunks/main-396265f3b83d3285.js","apps/web/.next/static/chunks/main-app-85d0d6820989dc6e.js","apps/web/.next/static/chunks/pages","apps/web/.next/static/chunks/pages/_app-32ee63fa91347547.js","apps/web/.next/static/chunks/pages/_error-79ee453ce9bad74d.js","apps/web/.next/static/chunks/polyfills-42372ed130431b0a.js","apps/web/.next/static/chunks/webpack-843aca0629275769.js","apps/web/.next/static/css","apps/web/.next/static/css/68c75141fb380fcd.css","apps/web/.next/static/media","apps/web/.next/static/media/19cfc7226ec3afaa-s.woff2","apps/web/.next/static/media/21350d82a1f187e9-s.woff2","apps/web/.next/static/media/636a5ac981f94f8b-s.p.woff2","apps/web/.next/static/media/6fe53d21e6e7ebd8-s.woff2","apps/web/.next/static/media/8e9860b6e62d6359-s.woff2","apps/web/.next/static/media/8ebc6e9dde468c4a-s.woff2","apps/web/.next/static/media/9e7b0a821b9dfcb4-s.woff2","apps/web/.next/static/media/ba9851c3c22cd980-s.woff2","apps/web/.next/static/media/c5fe6dc8356a8c31-s.woff2","apps/web/.next/static/media/df0a9ae256c0569c-s.woff2","apps/web/.next/static/media/e4af272ccee01ff0-s.p.woff2","apps/web/.next/trace","apps/web/.next/types","apps/web/.next/types/app","apps/web/.next/types/app/layout.ts","apps/web/.next/types/app/page.ts","apps/web/.next/types/package.json","apps/web/.turbo/turbo-build.log"]}